setup.py
BMI_OpenGMS_Engine/__init__.py
BMI_OpenGMS_Engine/bmiOpengmsEngine.py
BMI_OpenGMS_Engine.egg-info/PKG-INFO
BMI_OpenGMS_Engine.egg-info/SOURCES.txt
BMI_OpenGMS_Engine.egg-info/dependency_links.txt
BMI_OpenGMS_Engine.egg-info/requires.txt
BMI_OpenGMS_Engine.egg-info/top_level.txt
BMI_OpenGMS_Engine.egg-info/zip-safe
BMI_OpenGMS_Engine/mdl_python/AttributeSet.py
BMI_OpenGMS_Engine/mdl_python/Behavior.py
BMI_OpenGMS_Engine/mdl_python/IAttributeSet.py
BMI_OpenGMS_Engine/mdl_python/IBehavior.py
BMI_OpenGMS_Engine/mdl_python/IModelClass.py
BMI_OpenGMS_Engine/mdl_python/IRuntime.py
BMI_OpenGMS_Engine/mdl_python/ModelClass.py
BMI_OpenGMS_Engine/mdl_python/Runtime.py
BMI_OpenGMS_Engine/mdl_python/__init__.py
BMI_OpenGMS_Engine/mdl_python/mdl_test.py
BMI_OpenGMS_Engine/resource/license.txt
BMI_OpenGMS_Engine/resource/modeldatahandler.py
BMI_OpenGMS_Engine/resource/modelservicecontext.py
BMI_OpenGMS_Engine/resource/bmi/__init__.py
BMI_OpenGMS_Engine/resource/bmi/base.py
BMI_OpenGMS_Engine/resource/bmi/bmi.py
BMI_OpenGMS_Engine/resource/bmi/getter_setter.py
BMI_OpenGMS_Engine/resource/bmi/grid.py
BMI_OpenGMS_Engine/resource/bmi/grid_rectilinear.py
BMI_OpenGMS_Engine/resource/bmi/grid_structured_quad.py
BMI_OpenGMS_Engine/resource/bmi/grid_uniform_rectilinear.py
BMI_OpenGMS_Engine/resource/bmi/grid_unstructured.py
BMI_OpenGMS_Engine/resource/bmi/info.py
BMI_OpenGMS_Engine/resource/bmi/time.py
BMI_OpenGMS_Engine/resource/bmi/vars.py
BMI_OpenGMS_Engine/resource/template/init.pyt